wait_for_amqp/__init__.py
wait_for_amqp/run.py
wait_for_amqp-1.0.dist-info/LICENSE
wait_for_amqp-1.0.dist-info/METADATA
wait_for_amqp-1.0.dist-info/WHEEL
wait_for_amqp-1.0.dist-info/entry_points.txt
wait_for_amqp-1.0.dist-info/top_level.txt
wait_for_amqp-1.0.dist-info/RECORD
