Metadata-Version: 2.1
Name: wait-for-amqp
Version: 1.0
Summary: An utility to wait for an AMQP broker instance to become available
Home-page: https://github.com/smok-serwis/wait-for-amqp
Author: Piotr Maślanka
Author-email: piotrm@smok.co
License: UNKNOWN
Project-URL: Code, https://github.com/smok-serwis/wait-for-amqp
Project-URL: Issue tracker, https://github.com/smok-serwis/wait-for-amqp/issues
Keywords: amqp,ci,utility
Platform: UNKNOWN
Classifier: Programming Language :: Python
Classifier: Programming Language :: Python :: 2.7
Classifier: Programming Language :: Python :: 3.5
Classifier: Programming Language :: Python :: 3.6
Classifier: Programming Language :: Python :: 3.7
Classifier: Programming Language :: Python :: 3.8
Classifier: Programming Language :: Python :: Implementation :: CPython
Classifier: Programming Language :: Python :: Implementation :: PyPy
Classifier: Operating System :: POSIX
Classifier: Operating System :: OS Independent
Classifier: Development Status :: 5 - Production/Stable
Classifier: License :: OSI Approved :: MIT License
Classifier: Topic :: Utilities
Requires-Dist: coolamqp (>=1.0.2)
